kamiwaza_mlx/__init__.py
kamiwaza_mlx/distributed_runtime.py
kamiwaza_mlx/infer.py
kamiwaza_mlx/mem.sh
kamiwaza_mlx/server.py
kamiwaza_mlx/config/tool_parsers.json
kamiwaza_mlx/lib/parsers/tool/__init__.py
kamiwaza_mlx/lib/parsers/tool/base.py
kamiwaza_mlx/lib/parsers/tool/minimax_m2.py
kamiwaza_mlx/lib/parsers/tool/openai_json.py
kamiwaza_mlx-0.2.4.dist-info/METADATA
kamiwaza_mlx-0.2.4.dist-info/WHEEL
kamiwaza_mlx-0.2.4.dist-info/entry_points.txt
kamiwaza_mlx-0.2.4.dist-info/top_level.txt
kamiwaza_mlx-0.2.4.dist-info/RECORD
