Metadata-Version: 2.4
Name: kamiwaza-mlx
Version: 0.2.4
Summary: Unified MLX server & CLI (language and vision) with OpenAI-compatible endpoints
Author-email: Matt <opensource@kamiwaza.ai>
License: MIT License
Project-URL: Homepage, https://github.com/kamiwaza-ai/kamiwaza-mlx
Project-URL: Bug Tracker, https://github.com/kamiwaza-ai/kamiwaza-mlx/issues
Requires-Python: >=3.10
Requires-Dist: fastapi>=0.116.0
Requires-Dist: uvicorn[standard]>=0.34.0
Requires-Dist: pydantic>=2.8.0
Requires-Dist: requests>=2.31.0
Requires-Dist: Pillow>=11.0.0
Requires-Dist: mlx<0.31,>=0.30.1
Requires-Dist: mlx-lm<0.31,>=0.30.0
Requires-Dist: mlx-metal<0.31,>=0.30.1
Requires-Dist: mlx-vlm<0.4,>=0.3.9
Requires-Dist: torchvision>=0.24.0
